{
  "particDesc": [
    {
      "name": "Black Pawn 2",
      "id": "black-pawn-2",
      "isGroup": false,
      "sex": "UNKNOWN"
    },
    {
      "name": "Black Jesting Pawn",
      "id": "black-jesting-pawn",
      "isGroup": false,
      "sex": "MALE"
    },
    {
      "name": "Black Duke",
      "id": "black-duke",
      "isGroup": false,
      "sex": "MALE"
    },
    {
      "name": "White Duke",
      "id": "white-duke",
      "isGroup": false,
      "sex": "MALE"
    },
    {
      "name": "Fat Bishop Pawn",
      "id": "fat-bishop-pawn",
      "isGroup": false,
      "sex": "MALE"
    },
    {
      "name": "White King Pawn",
      "id": "white-king-pawn",
      "isGroup": false,
      "sex": "MALE"
    },
    {
      "id": "ignatius",
      "name": "Ignatius",
      "isGroup": false,
      "sex": "MALE"
    },
    {
      "id": "error",
      "name": "Error",
      "isGroup": false,
      "sex": "UNKNOWN"
    },
    {
      "id": "black_queen_pawn",
      "name": "Black Queen Pawn",
      "isGroup": false,
      "sex": "FEMALE"
    },
    {
      "id": "white_queen_pawn",
      "name": "White Queen Pawn",
      "isGroup": false,
      "sex": "FEMALE"
    },
    {
      "id": "black_bishop_pawn",
      "name": "Black Bishop Pawn",
      "isGroup": false,
      "sex": "MALE"
    },
    {
      "id": "black_bishop",
      "name": "Black Bishop",
      "isGroup": false,
      "sex": "MALE"
    },
    {
      "id": "white_bishop",
      "name": "White Bishop",
      "isGroup": false,
      "sex": "MALE"
    },
    {
      "id": "black_knight",
      "name": "Black Knight",
      "isGroup": false,
      "sex": "MALE"
    },
    {
      "id": "white_queen",
      "name": "White Queen",
      "isGroup": false,
      "sex": "FEMALE"
    },
    {
      "id": "black_pawn",
      "name": "Black Pawn",
      "isGroup": false,
      "sex": "MALE"
    },
    {
      "id": "white_king",
      "name": "White King",
      "isGroup": false,
      "sex": "MALE"
    },
    {
      "id": "white_knight",
      "name": "White Knight",
      "isGroup": false,
      "sex": "MALE"
    },
    {
      "id": "white_pawn",
      "name": "White Pawn",
      "isGroup": false,
      "sex": "MALE"
    },
    {
      "id": "white_knight_pawn",
      "name": "White Knight Pawn",
      "isGroup": false,
      "sex": "MALE"
    },
    {
      "id": "black_king",
      "name": "Black King",
      "isGroup": false,
      "sex": "MALE"
    },
    {
      "id": "black_queen",
      "name": "Black Queen",
      "isGroup": false,
      "sex": "FEMALE"
    },
    {
      "id": "black_knight_pawn",
      "name": "Black Knight Pawn",
      "isGroup": false,
      "sex": "MALE"
    },
    {
      "id": "captain_2",
      "name": "Captain 2",
      "isGroup": false,
      "sex": "MALE"
    },
    {
      "id": "fat_bishop",
      "name": "Fat Bishop",
      "isGroup": false,
      "sex": "MALE"
    },
    {
      "id": "white_bishop_pawn",
      "name": "White Bishop Pawn",
      "isGroup": false,
      "sex": "MALE"
    }
  ],
  "speeches": {
    "A07498-e100440": [
      "ignatius"
    ],
    "A07498-e100830": [
      "error"
    ],
    "A07498-e100890": [
      "ignatius"
    ],
    "A07498-e100910": [
      "error"
    ],
    "A07498-e100960": [
      "ignatius"
    ],
    "A07498-e100980": [
      "error"
    ],
    "A07498-e101020": [
      "ignatius"
    ],
    "A07498-e101060": [
      "error"
    ],
    "A07498-e101100": [
      "ignatius"
    ],
    "A07498-e101150": [
      "error"
    ],
    "A07498-e101200": [
      "ignatius"
    ],
    "A07498-e101220": [
      "error"
    ],
    "A07498-e101290": [
      "ignatius"
    ],
    "A07498-e101310": [
      "error"
    ],
    "A07498-e101330": [
      "ignatius"
    ],
    "A07498-e101420": [
      "error"
    ],
    "A07498-e101460": [
      "ignatius"
    ],
    "A07498-e101480": [
      "error"
    ],
    "A07498-e101500": [
      "ignatius"
    ],
    "A07498-e101540": [
      "error"
    ],
    "A07498-e101580": [
      "ignatius"
    ],
    "A07498-e101660": [
      "black_queen_pawn"
    ],
    "A07498-e101730": [
      "white_queen_pawn"
    ],
    "A07498-e101860": [
      "black_queen_pawn"
    ],
    "A07498-e101930": [
      "white_queen_pawn"
    ],
    "A07498-e101970": [
      "black_queen_pawn"
    ],
    "A07498-e102130": [
      "white_queen_pawn"
    ],
    "A07498-e102180": [
      "black_queen_pawn"
    ],
    "A07498-e102320": [
      "white_queen_pawn"
    ],
    "A07498-e102360": [
      "black_queen_pawn"
    ],
    "A07498-e102580": [
      "black_bishop_pawn"
    ],
    "A07498-e102600": [
      "black_queen_pawn"
    ],
    "A07498-e102620": [
      "black_bishop_pawn"
    ],
    "A07498-e102840": [
      "white_queen_pawn"
    ],
    "A07498-e102920": [
      "black_bishop_pawn"
    ],
    "A07498-e103020": [
      "white_queen_pawn"
    ],
    "A07498-e103060": [
      "black_bishop_pawn"
    ],
    "A07498-e103310": [
      "white_queen_pawn"
    ],
    "A07498-e103470": [
      "black_bishop_pawn"
    ],
    "A07498-e103490": [
      "white_queen_pawn"
    ],
    "A07498-e103540": [
      "black_bishop_pawn"
    ],
    "A07498-e103560": [
      "white_queen_pawn"
    ],
    "A07498-e103610": [],
    "A07498-e103710": [
      "white_queen_pawn"
    ],
    "A07498-e103730": [
      "black_bishop_pawn"
    ],
    "A07498-e103750": [
      "white_queen_pawn"
    ],
    "A07498-e103800": [
      "black_bishop_pawn"
    ],
    "A07498-e103850": [
      "white_queen_pawn"
    ],
    "A07498-e103870": [
      "black_bishop_pawn"
    ],
    "A07498-e103960": [
      "white_queen_pawn"
    ],
    "A07498-e104040": [],
    "A07498-e104150": [
      "white_queen_pawn"
    ],
    "A07498-e104200": [],
    "A07498-e104300": [
      "white_queen_pawn"
    ],
    "A07498-e104340": [],
    "A07498-e104390": [],
    "A07498-e104520": [],
    "A07498-e104570": [
      "white_queen_pawn"
    ],
    "A07498-e104590": [],
    "A07498-e104730": [
      "white_queen_pawn"
    ],
    "A07498-e104830": [],
    "A07498-e104880": [],
    "A07498-e104960": [],
    "A07498-e105020": [],
    "A07498-e105060": [],
    "A07498-e105080": [
      "black_knight"
    ],
    "A07498-e105390": [],
    "A07498-e105420": [
      "black_knight"
    ],
    "A07498-e105450": [
      "white_queen_pawn"
    ],
    "A07498-e105490": [
      "black_bishop_pawn"
    ],
    "A07498-e105540": [
      "black_knight"
    ],
    "A07498-e105640": [
      "black_bishop_pawn"
    ],
    "A07498-e105690": [
      "black_knight"
    ],
    "A07498-e105760": [
      "black_bishop_pawn"
    ],
    "A07498-e105790": [
      "black_knight"
    ],
    "A07498-e105820": [
      "black_bishop_pawn"
    ],
    "A07498-e105870": [
      "black_knight"
    ],
    "A07498-e105920": [],
    "A07498-e105980": [
      "black_knight"
    ],
    "A07498-e106010": [
      "black_bishop_pawn"
    ],
    "A07498-e106040": [
      "black_knight"
    ],
    "A07498-e106070": [
      "black_bishop_pawn"
    ],
    "A07498-e106100": [
      "black_knight"
    ],
    "A07498-e106130": [
      "black_bishop_pawn"
    ],
    "A07498-e106160": [
      "black_knight"
    ],
    "A07498-e106220": [],
    "A07498-e106260": [
      "black_knight"
    ],
    "A07498-e106290": [
      "black_bishop_pawn"
    ],
    "A07498-e106310": [
      "black_knight"
    ],
    "A07498-e106360": [
      "white-king-pawn"
    ],
    "A07498-e106490": [
      "black_knight"
    ],
    "A07498-e106590": [
      "white_queen_pawn"
    ],
    "A07498-e106700": [
      "black_bishop_pawn"
    ],
    "A07498-e106870": [
      "white_queen_pawn"
    ],
    "A07498-e106980": [
      "black_bishop_pawn"
    ],
    "A07498-e107040": [
      "white_queen_pawn"
    ],
    "A07498-e107110": [
      "black_bishop_pawn"
    ],
    "A07498-e107150": [
      "white_queen"
    ],
    "A07498-e107170": [
      "black_bishop_pawn"
    ],
    "A07498-e107210": [
      "white_queen_pawn"
    ],
    "A07498-e107230": [
      "black_bishop_pawn"
    ],
    "A07498-e107280": [
      "white_queen_pawn"
    ],
    "A07498-e107410": [
      "black_bishop_pawn"
    ],
    "A07498-e107510": [
      "white_queen_pawn"
    ],
    "A07498-e107560": [],
    "A07498-e107660": [
      "white_queen_pawn"
    ],
    "A07498-e107770": [],
    "A07498-e107890": [
      "white_queen_pawn"
    ],
    "A07498-e107910": [],
    "A07498-e107980": [
      "white_queen_pawn"
    ],
    "A07498-e108030": [],
    "A07498-e108090": [
      "white_queen_pawn"
    ],
    "A07498-e108110": [],
    "A07498-e108190": [
      "white_queen_pawn"
    ],
    "A07498-e108210": [],
    "A07498-e108250": [
      "white_queen_pawn"
    ],
    "A07498-e108270": [],
    "A07498-e108390": [
      "white_queen_pawn"
    ],
    "A07498-e108410": [],
    "A07498-e108480": [
      "white_queen_pawn"
    ],
    "A07498-e108520": [
      "black_bishop_pawn"
    ],
    "A07498-e108560": [
      "white_queen_pawn"
    ],
    "A07498-e108580": [],
    "A07498-e108630": [
      "white_queen_pawn"
    ],
    "A07498-e108660": [
      "white_bishop_pawn"
    ],
    "A07498-e108700": [
      "white_queen_pawn"
    ],
    "A07498-e108720": [
      "black_bishop_pawn"
    ],
    "A07498-e108780": [
      "white_queen_pawn"
    ],
    "A07498-e108820": [
      "black_bishop_pawn"
    ],
    "A07498-e108880": [
      "black_queen_pawn"
    ],
    "A07498-e108970": [],
    "A07498-e109040": [
      "black_bishop"
    ],
    "A07498-e109090": [
      "black_knight"
    ],
    "A07498-e109150": [],
    "A07498-e109190": [
      "black_bishop"
    ],
    "A07498-e109210": [
      "black_knight"
    ],
    "A07498-e109290": [
      "black_bishop"
    ],
    "A07498-e109310": [
      "black_knight"
    ],
    "A07498-e109350": [
      "black_bishop"
    ],
    "A07498-e109420": [
      "black_knight"
    ],
    "A07498-e109470": [],
    "A07498-e109510": [
      "black_bishop"
    ],
    "A07498-e109530": [
      "black_queen_pawn"
    ],
    "A07498-e109550": [
      "black_knight"
    ],
    "A07498-e109570": [
      "black_queen_pawn"
    ],
    "A07498-e109590": [
      "black_knight"
    ],
    "A07498-e109610": [],
    "A07498-e109660": [
      "black_bishop"
    ],
    "A07498-e109680": [
      "black_knight"
    ],
    "A07498-e109850": [
      "black_bishop"
    ],
    "A07498-e109890": [
      "black_knight"
    ],
    "A07498-e109980": [
      "black_bishop"
    ],
    "A07498-e110000": [
      "black_knight"
    ],
    "A07498-e110060": [
      "black_bishop"
    ],
    "A07498-e110080": [
      "black_knight"
    ],
    "A07498-e110190": [
      "black_queen_pawn"
    ],
    "A07498-e110240": [],
    "A07498-e110300": [
      "black_queen_pawn"
    ],
    "A07498-e110340": [],
    "A07498-e110390": [
      "black_queen_pawn"
    ],
    "A07498-e110440": [],
    "A07498-e110460": [
      "black_queen_pawn"
    ],
    "A07498-e110490": [
      "fat_bishop"
    ],
    "A07498-e110510": [
      "black_pawn"
    ],
    "A07498-e110530": [],
    "A07498-e110670": [
      "fat-bishop-pawn"
    ],
    "A07498-e110710": [],
    "A07498-e110750": [
      "fat-bishop-pawn"
    ],
    "A07498-e110770": [],
    "A07498-e111170": [
      "black_knight"
    ],
    "A07498-e111240": [
      "black_bishop"
    ],
    "A07498-e111280": [
      "black_knight"
    ],
    "A07498-e111440": [
      "black_bishop"
    ],
    "A07498-e111610": [
      "black_bishop"
    ],
    "A07498-e111630": [
      "white_king"
    ],
    "A07498-e111650": [],
    "A07498-e111730": [
      "black_knight"
    ],
    "A07498-e111750": [],
    "A07498-e111790": [
      "white_bishop"
    ],
    "A07498-e111810": [
      "black_knight"
    ],
    "A07498-e111850": [
      "black_bishop"
    ],
    "A07498-e111870": [
      "black_knight"
    ],
    "A07498-e111890": [
      "white_queen"
    ],
    "A07498-e111990": [
      "white_queen_pawn"
    ],
    "A07498-e112150": [
      "white_queen"
    ],
    "A07498-e112170": [
      "white_king"
    ],
    "A07498-e112220": [
      "white_queen_pawn"
    ],
    "A07498-e112300": [
      "white_king"
    ],
    "A07498-e112490": [
      "white_queen_pawn"
    ],
    "A07498-e112530": [
      "black_bishop"
    ],
    "A07498-e112610": [
      "white_bishop"
    ],
    "A07498-e112630": [
      "black_bishop"
    ],
    "A07498-e112670": [
      "white_knight"
    ],
    "A07498-e112730": [
      "black_knight"
    ],
    "A07498-e112960": [
      "white_queen_pawn"
    ],
    "A07498-e113030": [
      "black_knight"
    ],
    "A07498-e113080": [
      "white_bishop"
    ],
    "A07498-e113100": [
      "black_knight"
    ],
    "A07498-e113170": [
      "white_queen_pawn"
    ],
    "A07498-e113190": [
      "black_knight"
    ],
    "A07498-e113300": [
      "white_queen_pawn"
    ],
    "A07498-e113340": [
      "black_knight"
    ],
    "A07498-e113390": [
      "white_queen_pawn"
    ],
    "A07498-e113430": [
      "black_knight"
    ],
    "A07498-e113480": [
      "white_knight"
    ],
    "A07498-e113500": [
      "black_knight"
    ],
    "A07498-e113520": [
      "white_pawn"
    ],
    "A07498-e113540": [
      "white_king"
    ],
    "A07498-e113560": [
      "black_knight"
    ],
    "A07498-e113600": [
      "white_knight_pawn"
    ],
    "A07498-e113620": [
      "black_knight"
    ],
    "A07498-e113640": [
      "white_king"
    ],
    "A07498-e113660": [
      "white_queen_pawn"
    ],
    "A07498-e113720": [
      "black_knight"
    ],
    "A07498-e113760": [
      "white_knight_pawn"
    ],
    "A07498-e113780": [
      "black_knight"
    ],
    "A07498-e113840": [
      "white_king"
    ],
    "A07498-e113910": [
      "black_knight"
    ],
    "A07498-e113950": [
      "white_knight"
    ],
    "A07498-e114000": [
      "black_knight"
    ],
    "A07498-e114020": [
      "white_queen_pawn"
    ],
    "A07498-e114080": [
      "white_knight"
    ],
    "A07498-e114140": [
      "white-duke"
    ],
    "A07498-e114160": [
      "white_knight"
    ],
    "A07498-e114180": [],
    "A07498-e114220": [
      "black_knight"
    ],
    "A07498-e114240": [
      "black_bishop"
    ],
    "A07498-e114260": [
      "black_knight"
    ],
    "A07498-e114370": [
      "black_king"
    ],
    "A07498-e114390": [
      "black_queen"
    ],
    "A07498-e114410": [
      "black_bishop"
    ],
    "A07498-e114430": [
      "black_knight"
    ],
    "A07498-e114500": [
      "black-duke"
    ],
    "A07498-e114540": [
      "black_knight"
    ],
    "A07498-e114560": [
      "white_queen_pawn"
    ],
    "A07498-e114630": [
      "fat_bishop"
    ],
    "A07498-e114830": [
      "black_knight"
    ],
    "A07498-e114900": [],
    "A07498-e114920": [
      "black_knight"
    ],
    "A07498-e114960": [],
    "A07498-e115030": [
      "black_knight"
    ],
    "A07498-e115110": [
      "black_knight"
    ],
    "A07498-e115190": [],
    "A07498-e115320": [
      "black_knight"
    ],
    "A07498-e115470": [],
    "A07498-e115950": [
      "black_knight_pawn"
    ],
    "A07498-e115990": [
      "black_knight"
    ],
    "A07498-e116030": [],
    "A07498-e116070": [
      "black_knight"
    ],
    "A07498-e116140": [
      "black_knight_pawn"
    ],
    "A07498-e116160": [
      "black_knight"
    ],
    "A07498-e116200": [
      "black_knight_pawn"
    ],
    "A07498-e116260": [
      "black_knight"
    ],
    "A07498-e116300": [
      "black_knight_pawn"
    ],
    "A07498-e116320": [
      "black_knight"
    ],
    "A07498-e116360": [],
    "A07498-e116380": [
      "black_knight"
    ],
    "A07498-e116420": [
      "black_knight_pawn"
    ],
    "A07498-e116440": [
      "black_knight"
    ],
    "A07498-e116500": [],
    "A07498-e116520": [
      "black_knight"
    ],
    "A07498-e116570": [],
    "A07498-e116620": [
      "black_knight"
    ],
    "A07498-e116640": [],
    "A07498-e116710": [
      "black_knight"
    ],
    "A07498-e116760": [
      "black_bishop"
    ],
    "A07498-e116780": [
      "black_knight"
    ],
    "A07498-e116820": [
      "white_king"
    ],
    "A07498-e116870": [
      "black_knight"
    ],
    "A07498-e116890": [
      "white_king"
    ],
    "A07498-e117010": [
      "white-duke"
    ],
    "A07498-e117090": [
      "white_king"
    ],
    "A07498-e117150": [
      "black_knight"
    ],
    "A07498-e117230": [
      "white_knight"
    ],
    "A07498-e117250": [
      "white_king"
    ],
    "A07498-e117270": [
      "white_queen_pawn"
    ],
    "A07498-e117310": [
      "black_knight"
    ],
    "A07498-e117420": [
      "white_king"
    ],
    "A07498-e117520": [
      "black_knight"
    ],
    "A07498-e117570": [
      "white-duke"
    ],
    "A07498-e117610": [
      "white_knight"
    ],
    "A07498-e117660": [
      "black_queen_pawn"
    ],
    "A07498-e117740": [
      "black_queen"
    ],
    "A07498-e117760": [
      "black_knight"
    ],
    "A07498-e117810": [
      "black_queen_pawn"
    ],
    "A07498-e117850": [
      "black_queen"
    ],
    "A07498-e117870": [
      "black_knight"
    ],
    "A07498-e117910": [
      "black_queen_pawn"
    ],
    "A07498-e117950": [
      "black_queen"
    ],
    "A07498-e117970": [
      "black_knight"
    ],
    "A07498-e117990": [
      "black_queen_pawn"
    ],
    "A07498-e118050": [
      "black_queen"
    ],
    "A07498-e118090": [
      "white_king"
    ],
    "A07498-e118110": [
      "black_queen_pawn"
    ],
    "A07498-e118160": [
      "white_queen_pawn"
    ],
    "A07498-e118210": [
      "white_king"
    ],
    "A07498-e118230": [
      "black_knight"
    ],
    "A07498-e118250": [
      "black_king"
    ],
    "A07498-e118270": [
      "black_queen"
    ],
    "A07498-e118290": [
      "black_bishop"
    ],
    "A07498-e118310": [
      "black-duke"
    ],
    "A07498-e118330": [
      "black_queen_pawn"
    ],
    "A07498-e118350": [
      "black_knight"
    ],
    "A07498-e118370": [
      "black_queen_pawn"
    ],
    "A07498-e118430": [
      "black_knight"
    ],
    "A07498-e118490": [
      "black_knight"
    ],
    "A07498-e118510": [
      "black_knight"
    ],
    "A07498-e118570": [
      "black_bishop"
    ],
    "A07498-e118610": [
      "black_knight"
    ],
    "A07498-e118650": [
      "black_king"
    ],
    "A07498-e118690": [
      "black_knight"
    ],
    "A07498-e118710": [
      "white_knight"
    ],
    "A07498-e118770": [
      "black_knight"
    ],
    "A07498-e118860": [
      "white_king"
    ],
    "A07498-e118880": [
      "white-duke"
    ],
    "A07498-e118900": [
      "white_queen"
    ],
    "A07498-e118920": [
      "white_king"
    ],
    "A07498-e119080": [
      "white_bishop"
    ],
    "A07498-e119100": [
      "white_king"
    ],
    "A07498-e119140": [
      "black_king"
    ],
    "A07498-e119160": [
      "black_knight"
    ],
    "A07498-e119200": [],
    "A07498-e119270": [
      "white_king"
    ],
    "A07498-e119310": [],
    "A07498-e119370": [
      "white_king"
    ],
    "A07498-e119390": [
      "black_king"
    ],
    "A07498-e119410": [
      "black_knight"
    ],
    "A07498-e119430": [],
    "A07498-e119470": [
      "white_knight"
    ],
    "A07498-e119490": [
      "fat_bishop"
    ],
    "A07498-e119540": [
      "black_king"
    ],
    "A07498-e119560": [
      "white-duke"
    ],
    "A07498-e119590": [],
    "A07498-e119630": [
      "black_knight"
    ],
    "A07498-e119670": [
      "black_king"
    ],
    "A07498-e119690": [
      "black-duke"
    ],
    "A07498-e119710": [],
    "A07498-e119730": [
      "black-duke"
    ],
    "A07498-e119750": [
      "white_knight_pawn"
    ],
    "A07498-e119770": [
      "black_knight"
    ],
    "A07498-e119830": [
      "white-king-pawn"
    ],
    "A07498-e119850": [
      "black_knight"
    ],
    "A07498-e119910": [
      "white_queen_pawn"
    ],
    "A07498-e119970": [
      "black_queen_pawn"
    ],
    "A07498-e120010": [
      "white_queen_pawn"
    ],
    "A07498-e120030": [
      "black_queen_pawn"
    ],
    "A07498-e120070": [
      "white_queen_pawn"
    ],
    "A07498-e120090": [
      "black_queen_pawn"
    ],
    "A07498-e120130": [
      "white_queen_pawn"
    ],
    "A07498-e120150": [
      "black_queen_pawn"
    ],
    "A07498-e120200": [
      "white_queen_pawn"
    ],
    "A07498-e120240": [
      "black_queen_pawn"
    ],
    "A07498-e120280": [
      "white_queen_pawn"
    ],
    "A07498-e120300": [
      "black_queen_pawn"
    ],
    "A07498-e120380": [
      "white_queen_pawn"
    ],
    "A07498-e120430": [
      "black_queen_pawn"
    ],
    "A07498-e120470": [
      "white_queen_pawn"
    ],
    "A07498-e120490": [
      "black_queen_pawn"
    ],
    "A07498-e120540": [
      "white_queen_pawn"
    ],
    "A07498-e120580": [
      "black_queen_pawn"
    ],
    "A07498-e120640": [
      "black-jesting-pawn"
    ],
    "A07498-e120720": [
      "white_pawn"
    ],
    "A07498-e120770": [
      "black_pawn"
    ],
    "A07498-e120820": [
      "white_pawn"
    ],
    "A07498-e120860": [
      "black_pawn"
    ],
    "A07498-e120900": [
      "white_queen_pawn"
    ],
    "A07498-e120950": [
      "black_pawn"
    ],
    "A07498-e121010": [
      "white_pawn"
    ],
    "A07498-e121050": [
      "black_pawn"
    ],
    "A07498-e121110": [
      "white_pawn"
    ],
    "A07498-e121180": [
      "black-pawn-2"
    ],
    "A07498-e121220": [
      "white_pawn"
    ],
    "A07498-e121280": [
      "black_pawn"
    ],
    "A07498-e121300": [
      "white_pawn"
    ],
    "A07498-e121320": [
      "black-pawn-2"
    ],
    "A07498-e121340": [
      "white_pawn"
    ],
    "A07498-e121360": [
      "black_pawn"
    ],
    "A07498-e121430": [
      "black_queen_pawn"
    ],
    "A07498-e121470": [
      "white_queen_pawn"
    ],
    "A07498-e121540": [
      "black_queen_pawn"
    ],
    "A07498-e121660": [
      "white_pawn"
    ],
    "A07498-e121680": [
      "black_pawn"
    ],
    "A07498-e121740": [
      "white_queen_pawn"
    ],
    "A07498-e121760": [
      "black_queen_pawn"
    ],
    "A07498-e121860": [
      "white_queen_pawn"
    ],
    "A07498-e121880": [
      "black_queen_pawn"
    ],
    "A07498-e121960": [
      "white_queen_pawn"
    ],
    "A07498-e121980": [
      "black_queen_pawn"
    ],
    "A07498-e122200": [
      "white_queen_pawn"
    ],
    "A07498-e122220": [
      "black_queen_pawn"
    ],
    "A07498-e122240": [
      "white_queen_pawn"
    ],
    "A07498-e122260": [
      "black_queen_pawn"
    ],
    "A07498-e122300": [
      "white_queen_pawn"
    ],
    "A07498-e122370": [
      "black_queen_pawn"
    ],
    "A07498-e122470": [
      "white_queen_pawn"
    ],
    "A07498-e122520": [
      "black_queen_pawn"
    ],
    "A07498-e122570": [
      "black_knight_pawn"
    ],
    "A07498-e122730": [
      "black_bishop_pawn"
    ],
    "A07498-e122750": [],
    "A07498-e122810": [
      "black_bishop_pawn"
    ],
    "A07498-e122860": [],
    "A07498-e122950": [
      "black_bishop_pawn"
    ],
    "A07498-e122970": [],
    "A07498-e122990": [
      "black_bishop_pawn"
    ],
    "A07498-e123100": [],
    "A07498-e123120": [
      "black_bishop_pawn"
    ],
    "A07498-e123160": [
      "white_queen_pawn"
    ],
    "A07498-e123180": [
      "black_queen_pawn"
    ],
    "A07498-e123200": [
      "white_queen_pawn"
    ],
    "A07498-e123240": [
      "black_queen_pawn"
    ],
    "A07498-e123310": [
      "white_queen_pawn"
    ],
    "A07498-e123350": [
      "black_queen_pawn"
    ],
    "A07498-e123400": [
      "white_queen_pawn"
    ],
    "A07498-e123510": [
      "black_queen_pawn"
    ],
    "A07498-e123530": [
      "white_queen_pawn"
    ],
    "A07498-e123590": [
      "black_queen_pawn"
    ],
    "A07498-e123680": [
      "white_queen_pawn"
    ],
    "A07498-e123700": [
      "black_queen_pawn"
    ],
    "A07498-e123810": [
      "black_bishop_pawn"
    ],
    "A07498-e123860": [
      "black_queen_pawn"
    ],
    "A07498-e123920": [],
    "A07498-e123960": [
      "black_queen_pawn"
    ],
    "A07498-e124000": [],
    "A07498-e124050": [
      "black_queen_pawn"
    ],
    "A07498-e124120": [
      "black_bishop_pawn"
    ],
    "A07498-e124170": [
      "black_queen_pawn"
    ],
    "A07498-e124190": [],
    "A07498-e124240": [
      "white_queen_pawn"
    ],
    "A07498-e124310": [
      "black_bishop_pawn"
    ],
    "A07498-e124360": [
      "white_queen_pawn"
    ],
    "A07498-e124380": [
      "black_queen_pawn"
    ],
    "A07498-e124430": [
      "white_queen_pawn"
    ],
    "A07498-e124450": [],
    "A07498-e124470": [
      "white_queen_pawn"
    ],
    "A07498-e124510": [
      "black_bishop_pawn"
    ],
    "A07498-e124530": [
      "black_queen_pawn"
    ],
    "A07498-e124660": [
      "black_bishop_pawn"
    ],
    "A07498-e124720": [
      "white_queen_pawn"
    ],
    "A07498-e124860": [],
    "A07498-e124920": [
      "black_queen_pawn"
    ],
    "A07498-e124960": [
      "black_bishop_pawn"
    ],
    "A07498-e124980": [
      "black_queen_pawn"
    ],
    "A07498-e125050": [
      "black_bishop_pawn"
    ],
    "A07498-e125120": [
      "white_queen_pawn"
    ],
    "A07498-e125140": [
      "black_queen_pawn"
    ],
    "A07498-e125260": [
      "black_knight"
    ],
    "A07498-e125420": [],
    "A07498-e125500": [
      "black_knight"
    ],
    "A07498-e125640": [],
    "A07498-e125660": [
      "black_knight"
    ],
    "A07498-e125750": [],
    "A07498-e125770": [
      "black_knight"
    ],
    "A07498-e126140": [],
    "A07498-e126160": [
      "black_knight"
    ],
    "A07498-e126240": [],
    "A07498-e126260": [],
    "A07498-e126320": [
      "black_knight"
    ],
    "A07498-e126340": [
      "black_knight_pawn"
    ],
    "A07498-e126380": [
      "black_knight"
    ],
    "A07498-e126440": [],
    "A07498-e126480": [
      "black_knight"
    ],
    "A07498-e126570": [
      "fat_bishop"
    ],
    "A07498-e126610": [
      "black_knight"
    ],
    "A07498-e126630": [],
    "A07498-e126670": [
      "black_knight"
    ],
    "A07498-e126720": [],
    "A07498-e126740": [
      "black_knight"
    ],
    "A07498-e126760": [],
    "A07498-e126780": [
      "black_knight"
    ],
    "A07498-e126820": [
      "fat_bishop"
    ],
    "A07498-e126840": [
      "black_knight"
    ],
    "A07498-e126860": [
      "black_knight_pawn"
    ],
    "A07498-e126900": [
      "fat_bishop"
    ],
    "A07498-e126940": [
      "black_knight_pawn"
    ],
    "A07498-e126980": [],
    "A07498-e127040": [
      "black_knight_pawn"
    ],
    "A07498-e127120": [
      "black_knight"
    ],
    "A07498-e127160": [
      "black_knight"
    ],
    "A07498-e127210": [
      "fat_bishop"
    ],
    "A07498-e127260": [
      "black_knight"
    ],
    "A07498-e127300": [
      "black_knight"
    ],
    "A07498-e127360": [
      "white_knight"
    ],
    "A07498-e127420": [
      "white-duke"
    ],
    "A07498-e127470": [
      "white_knight"
    ],
    "A07498-e127540": [
      "white-duke"
    ],
    "A07498-e127610": [
      "white_king"
    ],
    "A07498-e127650": [
      "black_knight"
    ],
    "A07498-e127920": [
      "white_knight"
    ],
    "A07498-e127940": [
      "black_knight"
    ],
    "A07498-e127990": [
      "white_knight"
    ],
    "A07498-e128030": [
      "black_knight"
    ],
    "A07498-e128090": [
      "white_queen"
    ],
    "A07498-e128230": [],
    "A07498-e128280": [
      "white_queen"
    ],
    "A07498-e128300": [],
    "A07498-e128380": [
      "white_queen"
    ],
    "A07498-e128400": [
      "white_bishop"
    ],
    "A07498-e128420": [],
    "A07498-e128460": [
      "white_bishop"
    ],
    "A07498-e128550": [
      "white_queen"
    ],
    "A07498-e128570": [
      "white_knight"
    ],
    "A07498-e128630": [
      "white_queen"
    ],
    "A07498-e128650": [
      "white_knight"
    ],
    "A07498-e128880": [
      "white_queen"
    ],
    "A07498-e128900": [
      "white_knight"
    ],
    "A07498-e128940": [
      "white_queen"
    ],
    "A07498-e128960": [
      "white_knight"
    ],
    "A07498-e129000": [
      "white_queen"
    ],
    "A07498-e129020": [
      "white_knight"
    ],
    "A07498-e129060": [],
    "A07498-e129130": [
      "black_knight"
    ],
    "A07498-e129180": [],
    "A07498-e129200": [
      "black_knight"
    ],
    "A07498-e129240": [
      "black_bishop_pawn"
    ],
    "A07498-e129260": [
      "black_knight"
    ],
    "A07498-e129310": [],
    "A07498-e129430": [
      "black_king"
    ],
    "A07498-e129470": [
      "black_knight"
    ],
    "A07498-e129490": [
      "white_king"
    ],
    "A07498-e129510": [
      "black_king"
    ],
    "A07498-e129550": [
      "black_queen"
    ],
    "A07498-e129600": [
      "white_knight"
    ],
    "A07498-e129620": [
      "white-duke"
    ],
    "A07498-e129670": [
      "black_knight"
    ],
    "A07498-e129750": [
      "white_knight"
    ],
    "A07498-e129770": [
      "white-duke"
    ],
    "A07498-e129910": [
      "black_knight"
    ],
    "A07498-e129950": [
      "black_king"
    ],
    "A07498-e130010": [
      "white_queen_pawn"
    ],
    "A07498-e130100": [
      "black_bishop_pawn"
    ],
    "A07498-e130170": [
      "white_queen_pawn"
    ],
    "A07498-e130440": [
      "black_bishop_pawn"
    ],
    "A07498-e130510": [
      "white_queen_pawn"
    ],
    "A07498-e130560": [
      "black_bishop_pawn"
    ],
    "A07498-e130630": [
      "white_queen_pawn"
    ],
    "A07498-e130680": [
      "black_bishop_pawn"
    ],
    "A07498-e130700": [
      "white_queen_pawn"
    ],
    "A07498-e130760": [
      "black_bishop_pawn"
    ],
    "A07498-e130890": [
      "white_queen_pawn"
    ],
    "A07498-e130940": [
      "black_bishop_pawn"
    ],
    "A07498-e130960": [],
    "A07498-e130980": [
      "black_bishop_pawn"
    ],
    "A07498-e131000": [
      "white_queen_pawn"
    ],
    "A07498-e131040": [],
    "A07498-e131060": [],
    "A07498-e131100": [
      "black_queen_pawn"
    ],
    "A07498-e131130": [],
    "A07498-e131150": [],
    "A07498-e131190": [],
    "A07498-e131210": [
      "black_queen_pawn"
    ],
    "A07498-e131240": [],
    "A07498-e131260": [
      "black_queen_pawn"
    ],
    "A07498-e131300": [
      "black_bishop_pawn"
    ],
    "A07498-e131340": [
      "black_queen_pawn"
    ],
    "A07498-e131370": [],
    "A07498-e131420": [
      "black_queen_pawn"
    ],
    "A07498-e131450": [
      "black_bishop_pawn"
    ],
    "A07498-e131470": [
      "black_queen_pawn"
    ],
    "A07498-e131520": [],
    "A07498-e131540": [
      "black_queen_pawn"
    ],
    "A07498-e131680": [
      "black_bishop_pawn"
    ],
    "A07498-e131700": [
      "black_queen_pawn"
    ],
    "A07498-e131770": [
      "black_bishop_pawn"
    ],
    "A07498-e131820": [
      "white_bishop_pawn"
    ],
    "A07498-e131840": [
      "white_queen_pawn"
    ],
    "A07498-e131860": [
      "black_bishop_pawn"
    ],
    "A07498-e131880": [
      "black_queen_pawn"
    ],
    "A07498-e131940": [
      "black_bishop_pawn"
    ],
    "A07498-e131960": [
      "black_knight_pawn"
    ],
    "A07498-e131980": [
      "white_queen_pawn"
    ],
    "A07498-e132030": [
      "black_knight_pawn"
    ],
    "A07498-e132050": [
      "white_queen_pawn"
    ],
    "A07498-e132110": [
      "white_knight"
    ],
    "A07498-e132150": [
      "black_knight"
    ],
    "A07498-e132200": [
      "white_knight"
    ],
    "A07498-e132220": [
      "black_knight"
    ],
    "A07498-e132460": [
      "white_knight"
    ],
    "A07498-e132480": [
      "black_knight"
    ],
    "A07498-e132750": [
      "white_knight"
    ],
    "A07498-e132800": [
      "black_king"
    ],
    "A07498-e132820": [
      "black_queen"
    ],
    "A07498-e132840": [
      "white_knight"
    ],
    "A07498-e132860": [
      "white-duke"
    ],
    "A07498-e132910": [
      "white_knight"
    ],
    "A07498-e132950": [
      "black_knight"
    ],
    "A07498-e133050": [
      "white_knight"
    ],
    "A07498-e133110": [
      "black_knight"
    ],
    "A07498-e133170": [
      "white_knight"
    ],
    "A07498-e133190": [
      "black_knight"
    ],
    "A07498-e133250": [
      "white_knight"
    ],
    "A07498-e133270": [
      "black_knight"
    ],
    "A07498-e133470": [
      "white_knight"
    ],
    "A07498-e133490": [
      "black_knight"
    ],
    "A07498-e133540": [
      "white_knight"
    ],
    "A07498-e133610": [
      "black_knight"
    ],
    "A07498-e133730": [
      "white_knight"
    ],
    "A07498-e133750": [
      "black-duke"
    ],
    "A07498-e133770": [
      "white-duke"
    ],
    "A07498-e133820": [
      "black_knight"
    ],
    "A07498-e133840": [
      "white-duke"
    ],
    "A07498-e133890": [
      "black_knight"
    ],
    "A07498-e133970": [
      "white-duke"
    ],
    "A07498-e133990": [
      "black_knight"
    ],
    "A07498-e134080": [
      "black-duke"
    ],
    "A07498-e134100": [
      "white_knight"
    ],
    "A07498-e134150": [
      "black_knight"
    ],
    "A07498-e134200": [
      "white_knight"
    ],
    "A07498-e134240": [
      "black_knight"
    ],
    "A07498-e134260": [
      "white_knight"
    ],
    "A07498-e134310": [
      "black_knight"
    ],
    "A07498-e134430": [
      "black-duke"
    ],
    "A07498-e134450": [
      "black_knight"
    ],
    "A07498-e134470": [
      "white_knight"
    ],
    "A07498-e134520": [
      "black_knight"
    ],
    "A07498-e134550": [
      "white_knight"
    ],
    "A07498-e134570": [
      "white-duke"
    ],
    "A07498-e134590": [
      "black_knight"
    ],
    "A07498-e134610": [
      "black_queen"
    ],
    "A07498-e134640": [
      "white_knight"
    ],
    "A07498-e134710": [
      "white_queen"
    ],
    "A07498-e134750": [
      "white_knight"
    ],
    "A07498-e134800": [
      "white_knight"
    ],
    "A07498-e134930": [],
    "A07498-e134950": [],
    "A07498-e134970": [
      "black-jesting-pawn"
    ],
    "A07498-e135050": [],
    "A07498-e135100": [
      "black-jesting-pawn"
    ],
    "A07498-e135140": [],
    "A07498-e135180": [
      "black_queen_pawn"
    ],
    "A07498-e135200": [
      "white_knight"
    ],
    "A07498-e135220": [
      "white_knight"
    ],
    "A07498-e135260": [],
    "A07498-e135300": [
      "white_queen"
    ],
    "A07498-e135320": [],
    "A07498-e135340": [
      "white_knight"
    ],
    "A07498-e135380": [],
    "A07498-e135430": [
      "white-duke"
    ],
    "A07498-e135480": [],
    "A07498-e135530": [
      "white_knight"
    ]
  }
}